<root annotationID="0" passageID="545006">
  <attributes />
  <layer layerID="0">
    <attributes />
    <extra doc="[[], [], [], []]" />
    <node ID="0.1" type="Word">
      <attributes paragraph="1" paragraph_position="1" text="Contemporary" />
      <extra dep="nsubj" ent_iob="2" ent_type="" head="1" lemma="contemporary" orig_paragraph="1" orth="Contemporary" pos="ADJ" prefix="C" shape="Xxxxx" suffix="ary" tag="JJ" />
    </node>
    <node ID="0.2" type="Word">
      <attributes paragraph="1" paragraph_position="2" text="reports" />
      <extra dep="nsubjpass" ent_iob="2" ent_type="" head="19" lemma="report" orig_paragraph="1" orth="reports" pos="NOUN" prefix="r" shape="xxxx" suffix="rts" tag="NNS" />
    </node>
    <node ID="0.3" type="Word">
      <attributes paragraph="1" paragraph_position="3" text="that" />
      <extra dep="mark" ent_iob="2" ent_type="" head="4" lemma="that" orig_paragraph="1" orth="that" pos="ADP" prefix="t" shape="xxxx" suffix="hat" tag="IN" />
    </node>
    <node ID="0.4" type="Word">
      <attributes paragraph="1" paragraph_position="4" text="Jack" />
      <extra dep="compound" ent_iob="3" ent_type="PERSON" head="1" lemma="jack" orig_paragraph="1" orth="Jack" pos="PROPN" prefix="J" shape="Xxxx" suffix="ack" tag="NNP" />
    </node>
    <node ID="0.5" type="Word">
      <attributes paragraph="1" paragraph_position="5" text="Warner" />
      <extra dep="nsubj" ent_iob="1" ent_type="PERSON" head="2" lemma="warner" orig_paragraph="1" orth="Warner" pos="PROPN" prefix="W" shape="Xxxxx" suffix="ner" tag="NNP" />
    </node>
    <node ID="0.6" type="Word">
      <attributes paragraph="1" paragraph_position="6" text="had" />
      <extra dep="aux" ent_iob="2" ent_type="" head="1" lemma="have" orig_paragraph="1" orth="had" pos="VERB" prefix="h" shape="xxx" suffix="had" tag="VBD" />
    </node>
    <node ID="0.7" type="Word">
      <attributes paragraph="1" paragraph_position="7" text="banned" />
      <extra dep="ccomp" ent_iob="2" ent_type="" head="-5" lemma="ban" orig_paragraph="1" orth="banned" pos="VERB" prefix="b" shape="xxxx" suffix="ned" tag="VBN" />
    </node>
    <node ID="0.8" type="Word">
      <attributes paragraph="1" paragraph_position="8" text="the" />
      <extra dep="det" ent_iob="2" ent_type="" head="1" lemma="the" orig_paragraph="1" orth="the" pos="DET" prefix="t" shape="xxx" suffix="the" tag="DT" />
    </node>
    <node ID="0.9" type="Word">
      <attributes paragraph="1" paragraph_position="9" text="use" />
      <extra dep="dobj" ent_iob="2" ent_type="" head="-2" lemma="use" orig_paragraph="1" orth="use" pos="NOUN" prefix="u" shape="xxx" suffix="use" tag="NN" />
    </node>
    <node ID="0.10" type="Word">
      <attributes paragraph="1" paragraph_position="10" text="of" />
      <extra dep="prep" ent_iob="2" ent_type="" head="-1" lemma="of" orig_paragraph="1" orth="of" pos="ADP" prefix="o" shape="xx" suffix="of" tag="IN" />
    </node>
    <node ID="0.11" type="Word">
      <attributes paragraph="1" paragraph_position="11" text="the" />
      <extra dep="det" ent_iob="2" ent_type="" head="2" lemma="the" orig_paragraph="1" orth="the" pos="DET" prefix="t" shape="xxx" suffix="the" tag="DT" />
    </node>
    <node ID="0.12" type="Word">
      <attributes paragraph="1" paragraph_position="12" text="German" />
      <extra dep="amod" ent_iob="3" ent_type="NORP" head="1" lemma="german" orig_paragraph="1" orth="German" pos="ADJ" prefix="G" shape="Xxxxx" suffix="man" tag="JJ" />
    </node>
    <node ID="0.13" type="Word">
      <attributes paragraph="1" paragraph_position="13" text="language" />
      <extra dep="pobj" ent_iob="2" ent_type="" head="-3" lemma="language" orig_paragraph="1" orth="language" pos="NOUN" prefix="l" shape="xxxx" suffix="age" tag="NN" />
    </node>
    <node ID="0.14" type="Word">
      <attributes paragraph="1" paragraph_position="14" text="throughout" />
      <extra dep="prep" ent_iob="2" ent_type="" head="-5" lemma="throughout" orig_paragraph="1" orth="throughout" pos="ADP" prefix="t" shape="xxxx" suffix="out" tag="IN" />
    </node>
    <node ID="0.15" type="Word">
      <attributes paragraph="1" paragraph_position="15" text="the" />
      <extra dep="det" ent_iob="2" ent_type="" head="1" lemma="the" orig_paragraph="1" orth="the" pos="DET" prefix="t" shape="xxx" suffix="the" tag="DT" />
    </node>
    <node ID="0.16" type="Word">
      <attributes paragraph="1" paragraph_position="16" text="company" />
      <extra dep="poss" ent_iob="2" ent_type="" head="3" lemma="company" orig_paragraph="1" orth="company" pos="NOUN" prefix="c" shape="xxxx" suffix="any" tag="NN" />
    </node>
    <node ID="0.17" type="Word">
      <attributes paragraph="1" paragraph_position="17" text="'s" />
      <extra dep="case" ent_iob="2" ent_type="" head="-1" lemma="'s" orig_paragraph="1" orth="'s" pos="PART" prefix="'" shape="'x" suffix="'s" tag="POS" />
    </node>
    <node ID="0.18" type="Word">
      <attributes paragraph="1" paragraph_position="18" text="Burbank" />
      <extra dep="compound" ent_iob="3" ent_type="GPE" head="1" lemma="burbank" orig_paragraph="1" orth="Burbank" pos="PROPN" prefix="B" shape="Xxxxx" suffix="ank" tag="NNP" />
    </node>
    <node ID="0.19" type="Word">
      <attributes paragraph="1" paragraph_position="19" text="studio" />
      <extra dep="pobj" ent_iob="2" ent_type="" head="-5" lemma="studio" orig_paragraph="1" orth="studio" pos="NOUN" prefix="s" shape="xxxx" suffix="dio" tag="NN" />
    </node>
    <node ID="0.20" type="Word">
      <attributes paragraph="1" paragraph_position="20" text="were" />
      <extra dep="auxpass" ent_iob="2" ent_type="" head="1" lemma="be" orig_paragraph="1" orth="were" pos="VERB" prefix="w" shape="xxxx" suffix="ere" tag="VBD" />
    </node>
    <node ID="0.21" type="Word">
      <attributes paragraph="1" paragraph_position="21" text="denied" />
      <extra dep="csubj" ent_iob="2" ent_type="" head="11" lemma="deny" orig_paragraph="1" orth="denied" pos="VERB" prefix="d" shape="xxxx" suffix="ied" tag="VBN" />
    </node>
    <node ID="0.22" type="Word">
      <attributes paragraph="1" paragraph_position="22" text="by" />
      <extra dep="agent" ent_iob="2" ent_type="" head="-1" lemma="by" orig_paragraph="1" orth="by" pos="ADP" prefix="b" shape="xx" suffix="by" tag="IN" />
    </node>
    <node ID="0.23" type="Word">
      <attributes paragraph="1" paragraph_position="23" text="studio" />
      <extra dep="compound" ent_iob="2" ent_type="" head="1" lemma="studio" orig_paragraph="1" orth="studio" pos="NOUN" prefix="s" shape="xxxx" suffix="dio" tag="NN" />
    </node>
    <node ID="0.24" type="Word">
      <attributes paragraph="1" paragraph_position="24" text="representatives" />
      <extra dep="pobj" ent_iob="2" ent_type="" head="-2" lemma="representative" orig_paragraph="1" orth="representatives" pos="NOUN" prefix="r" shape="xxxx" suffix="ves" tag="NNS" />
    </node>
    <node ID="0.25" type="Punctuation">
      <attributes paragraph="1" paragraph_position="25" text="," />
      <extra dep="punct" ent_iob="2" ent_type="" head="-1" lemma="," orig_paragraph="1" orth="," pos="PUNCT" prefix="," shape="," suffix="," tag="," />
    </node>
    <node ID="0.26" type="Word">
      <attributes paragraph="1" paragraph_position="26" text="who" />
      <extra dep="nsubj" ent_iob="2" ent_type="" head="1" lemma="who" orig_paragraph="1" orth="who" pos="NOUN" prefix="w" shape="xxx" suffix="who" tag="WP" />
    </node>
    <node ID="0.27" type="Word">
      <attributes paragraph="1" paragraph_position="27" text="indicated" />
      <extra dep="relcl" ent_iob="2" ent_type="" head="-3" lemma="indicate" orig_paragraph="1" orth="indicated" pos="VERB" prefix="i" shape="xxxx" suffix="ted" tag="VBD" />
    </node>
    <node ID="0.28" type="Word">
      <attributes paragraph="1" paragraph_position="28" text="this" />
      <extra dep="det" ent_iob="2" ent_type="" head="1" lemma="this" orig_paragraph="1" orth="this" pos="DET" prefix="t" shape="xxxx" suffix="his" tag="DT" />
    </node>
    <node ID="0.29" type="Word">
      <attributes paragraph="1" paragraph_position="29" text="move" />
      <extra dep="dobj" ent_iob="2" ent_type="" head="-2" lemma="move" orig_paragraph="1" orth="move" pos="NOUN" prefix="m" shape="xxxx" suffix="ove" tag="NN" />
    </node>
    <node ID="0.30" type="Word">
      <attributes paragraph="1" paragraph_position="30" text="would" />
      <extra dep="aux" ent_iob="2" ent_type="" head="2" lemma="would" orig_paragraph="1" orth="would" pos="VERB" prefix="w" shape="xxxx" suffix="uld" tag="MD" />
    </node>
    <node ID="0.31" type="Word">
      <attributes paragraph="1" paragraph_position="31" text="have" />
      <extra dep="aux" ent_iob="2" ent_type="" head="1" lemma="have" orig_paragraph="1" orth="have" pos="VERB" prefix="h" shape="xxxx" suffix="ave" tag="VB" />
    </node>
    <node ID="0.32" type="Word">
      <attributes paragraph="1" paragraph_position="32" text="prevented" />
      <extra dep="ROOT" ent_iob="2" ent_type="" head="0" lemma="prevent" orig_paragraph="1" orth="prevented" pos="VERB" prefix="p" shape="xxxx" suffix="ted" tag="VBN" />
    </node>
    <node ID="0.33" type="Word">
      <attributes paragraph="1" paragraph_position="33" text="scores" />
      <extra dep="dobj" ent_iob="2" ent_type="" head="-1" lemma="score" orig_paragraph="1" orth="scores" pos="NOUN" prefix="s" shape="xxxx" suffix="res" tag="NNS" />
    </node>
    <node ID="0.34" type="Word">
      <attributes paragraph="1" paragraph_position="34" text="of" />
      <extra dep="prep" ent_iob="2" ent_type="" head="-1" lemma="of" orig_paragraph="1" orth="of" pos="ADP" prefix="o" shape="xx" suffix="of" tag="IN" />
    </node>
    <node ID="0.35" type="Word">
      <attributes paragraph="1" paragraph_position="35" text="studio" />
      <extra dep="compound" ent_iob="2" ent_type="" head="1" lemma="studio" orig_paragraph="1" orth="studio" pos="NOUN" prefix="s" shape="xxxx" suffix="dio" tag="NN" />
    </node>
    <node ID="0.36" type="Word">
      <attributes paragraph="1" paragraph_position="36" text="employees" />
      <extra dep="pobj" ent_iob="2" ent_type="" head="-2" lemma="employee" orig_paragraph="1" orth="employees" pos="NOUN" prefix="e" shape="xxxx" suffix="ees" tag="NNS" />
    </node>
    <node ID="0.37" type="Word">
      <attributes paragraph="1" paragraph_position="37" text="from" />
      <extra dep="prep" ent_iob="2" ent_type="" head="-5" lemma="from" orig_paragraph="1" orth="from" pos="ADP" prefix="f" shape="xxxx" suffix="rom" tag="IN" />
    </node>
    <node ID="0.38" type="Word">
      <attributes paragraph="1" paragraph_position="38" text="communicating" />
      <extra dep="pcomp" ent_iob="2" ent_type="" head="-1" lemma="communicate" orig_paragraph="1" orth="communicating" pos="VERB" prefix="c" shape="xxxx" suffix="ing" tag="VBG" />
    </node>
    <node ID="0.39" type="Word">
      <attributes paragraph="1" paragraph_position="39" text="with" />
      <extra dep="prep" ent_iob="2" ent_type="" head="-1" lemma="with" orig_paragraph="1" orth="with" pos="ADP" prefix="w" shape="xxxx" suffix="ith" tag="IN" />
    </node>
    <node ID="0.40" type="Word">
      <attributes paragraph="1" paragraph_position="40" text="each" />
      <extra dep="det" ent_iob="2" ent_type="" head="1" lemma="each" orig_paragraph="1" orth="each" pos="DET" prefix="e" shape="xxxx" suffix="ach" tag="DT" />
    </node>
    <node ID="0.41" type="Word">
      <attributes paragraph="1" paragraph_position="41" text="other" />
      <extra dep="pobj" ent_iob="2" ent_type="" head="-2" lemma="other" orig_paragraph="1" orth="other" pos="ADJ" prefix="o" shape="xxxx" suffix="her" tag="JJ" />
    </node>
    <node ID="0.42" type="Punctuation">
      <attributes paragraph="1" paragraph_position="42" text="." />
      <extra dep="punct" ent_iob="2" ent_type="" head="-10" lemma="." orig_paragraph="1" orth="." pos="PUNCT" prefix="." shape="." suffix="." tag="." />
    </node>
  </layer>
  <layer layerID="1">
    <attributes />
    <node ID="1.1" type="FN">
      <attributes />
      <edge toID="1.2" type="H">
        <attributes />
      </edge>
      <edge toID="1.3" type="U">
        <attributes />
      </edge>
    </node>
    <node ID="1.2" type="FN">
      <attributes />
      <edge toID="1.4" type="A">
        <attributes />
      </edge>
      <edge toID="1.5" type="P">
        <attributes />
      </edge>
      <edge toID="1.6" type="F">
        <attributes />
      </edge>
      <edge toID="1.7" type="A">
        <attributes />
      </edge>
    </node>
    <node ID="1.3" type="PNCT">
      <attributes />
      <edge toID="0.42" type="Terminal">
        <attributes />
      </edge>
    </node>
    <node ID="1.4" type="FN">
      <attributes />
      <edge toID="1.36" type="E">
        <attributes />
      </edge>
      <edge toID="1.37" type="C">
        <attributes />
      </edge>
      <edge toID="1.38" type="E">
        <attributes />
      </edge>
    </node>
    <node ID="1.5" type="FN">
      <attributes />
      <edge toID="0.21" type="Terminal">
        <attributes />
      </edge>
    </node>
    <node ID="1.6" type="FN">
      <attributes />
      <edge toID="0.20" type="Terminal">
        <attributes />
      </edge>
    </node>
    <node ID="1.7" type="FN">
      <attributes />
      <edge toID="1.8" type="R">
        <attributes />
      </edge>
      <edge toID="1.9" type="E">
        <attributes />
      </edge>
      <edge toID="1.10" type="C">
        <attributes />
      </edge>
      <edge toID="1.11" type="E">
        <attributes />
      </edge>
      <edge toID="1.12" type="U">
        <attributes />
      </edge>
    </node>
    <node ID="1.8" type="FN">
      <attributes />
      <edge toID="0.22" type="Terminal">
        <attributes />
      </edge>
    </node>
    <node ID="1.9" type="FN">
      <attributes />
      <edge toID="0.23" type="Terminal">
        <attributes />
      </edge>
    </node>
    <node ID="1.10" type="FN">
      <attributes />
      <edge toID="0.24" type="Terminal">
        <attributes />
      </edge>
    </node>
    <node ID="1.11" type="FN">
      <attributes />
      <edge toID="1.10" type="A">
        <attributes remote="True" />
      </edge>
      <edge toID="1.13" type="F">
        <attributes />
      </edge>
      <edge toID="1.14" type="P">
        <attributes />
      </edge>
      <edge toID="1.15" type="A">
        <attributes />
      </edge>
    </node>
    <node ID="1.12" type="PNCT">
      <attributes />
      <edge toID="0.25" type="Terminal">
        <attributes />
      </edge>
    </node>
    <node ID="1.13" type="FN">
      <attributes />
      <edge toID="0.26" type="Terminal">
        <attributes />
      </edge>
    </node>
    <node ID="1.14" type="FN">
      <attributes />
      <edge toID="0.27" type="Terminal">
        <attributes />
      </edge>
    </node>
    <node ID="1.15" type="FN">
      <attributes />
      <edge toID="1.16" type="A">
        <attributes />
      </edge>
      <edge toID="1.17" type="P">
        <attributes />
      </edge>
      <edge toID="1.18" type="F">
        <attributes />
      </edge>
      <edge toID="1.19" type="A">
        <attributes />
      </edge>
    </node>
    <node ID="1.16" type="FN">
      <attributes />
      <edge toID="1.34" type="E">
        <attributes />
      </edge>
      <edge toID="1.35" type="C">
        <attributes />
      </edge>
    </node>
    <node ID="1.17" type="FN">
      <attributes />
      <edge toID="1.32" type="F">
        <attributes />
      </edge>
      <edge toID="1.33" type="C">
        <attributes />
      </edge>
    </node>
    <node ID="1.18" type="FN">
      <attributes />
      <edge toID="0.31" type="Terminal">
        <attributes />
      </edge>
    </node>
    <node ID="1.19" type="FN">
      <attributes />
      <edge toID="1.20" type="A">
        <attributes />
      </edge>
      <edge toID="1.21" type="P">
        <attributes />
      </edge>
      <edge toID="1.22" type="D">
        <attributes />
      </edge>
    </node>
    <node ID="1.20" type="FN">
      <attributes />
      <edge toID="1.27" type="E">
        <attributes />
      </edge>
      <edge toID="1.28" type="E">
        <attributes />
      </edge>
      <edge toID="1.29" type="C">
        <attributes />
      </edge>
    </node>
    <node ID="1.21" type="FN">
      <attributes />
      <edge toID="1.25" type="F">
        <attributes />
      </edge>
      <edge toID="1.26" type="C">
        <attributes />
      </edge>
    </node>
    <node ID="1.22" type="FN">
      <attributes />
      <edge toID="1.23" type="R">
        <attributes />
      </edge>
      <edge toID="1.24" type="C">
        <attributes />
      </edge>
    </node>
    <node ID="1.23" type="FN">
      <attributes />
      <edge toID="0.39" type="Terminal">
        <attributes />
      </edge>
    </node>
    <node ID="1.24" type="FN">
      <attributes />
      <edge toID="0.40" type="Terminal">
        <attributes />
      </edge>
      <edge toID="0.41" type="Terminal">
        <attributes />
      </edge>
    </node>
    <node ID="1.25" type="FN">
      <attributes />
      <edge toID="0.37" type="Terminal">
        <attributes />
      </edge>
    </node>
    <node ID="1.26" type="FN">
      <attributes />
      <edge toID="0.38" type="Terminal">
        <attributes />
      </edge>
    </node>
    <node ID="1.27" type="FN">
      <attributes />
      <edge toID="1.30" type="C">
        <attributes />
      </edge>
      <edge toID="1.31" type="R">
        <attributes />
      </edge>
    </node>
    <node ID="1.28" type="FN">
      <attributes />
      <edge toID="0.35" type="Terminal">
        <attributes />
      </edge>
    </node>
    <node ID="1.29" type="FN">
      <attributes />
      <edge toID="0.36" type="Terminal">
        <attributes />
      </edge>
    </node>
    <node ID="1.30" type="FN">
      <attributes />
      <edge toID="0.33" type="Terminal">
        <attributes />
      </edge>
    </node>
    <node ID="1.31" type="FN">
      <attributes />
      <edge toID="0.34" type="Terminal">
        <attributes />
      </edge>
    </node>
    <node ID="1.32" type="FN">
      <attributes />
      <edge toID="0.30" type="Terminal">
        <attributes />
      </edge>
    </node>
    <node ID="1.33" type="FN">
      <attributes />
      <edge toID="0.32" type="Terminal">
        <attributes />
      </edge>
    </node>
    <node ID="1.34" type="FN">
      <attributes />
      <edge toID="0.28" type="Terminal">
        <attributes />
      </edge>
    </node>
    <node ID="1.35" type="FN">
      <attributes />
      <edge toID="0.29" type="Terminal">
        <attributes />
      </edge>
    </node>
    <node ID="1.36" type="FN">
      <attributes />
      <edge toID="0.1" type="Terminal">
        <attributes />
      </edge>
    </node>
    <node ID="1.37" type="FN">
      <attributes />
      <edge toID="0.2" type="Terminal">
        <attributes />
      </edge>
    </node>
    <node ID="1.38" type="FN">
      <attributes />
      <edge toID="1.39" type="F">
        <attributes />
      </edge>
      <edge toID="1.40" type="A">
        <attributes />
      </edge>
      <edge toID="1.41" type="P">
        <attributes />
      </edge>
      <edge toID="1.42" type="F">
        <attributes />
      </edge>
      <edge toID="1.43" type="D">
        <attributes />
      </edge>
      <edge toID="1.44" type="A">
        <attributes />
      </edge>
      <edge toID="1.45" type="A">
        <attributes />
      </edge>
    </node>
    <node ID="1.39" type="FN">
      <attributes />
      <edge toID="0.3" type="Terminal">
        <attributes />
      </edge>
    </node>
    <node ID="1.40" type="FN">
      <attributes />
      <edge toID="0.4" type="Terminal">
        <attributes />
      </edge>
      <edge toID="0.5" type="Terminal">
        <attributes />
      </edge>
    </node>
    <node ID="1.41" type="FN">
      <attributes />
      <edge toID="1.57" type="E">
        <attributes />
      </edge>
      <edge toID="1.58" type="C">
        <attributes />
      </edge>
    </node>
    <node ID="1.42" type="FN">
      <attributes />
      <edge toID="0.6" type="Terminal">
        <attributes />
      </edge>
    </node>
    <node ID="1.43" type="FN">
      <attributes />
      <edge toID="0.7" type="Terminal">
        <attributes />
      </edge>
    </node>
    <node ID="1.44" type="FN">
      <attributes />
      <edge toID="1.53" type="R">
        <attributes />
      </edge>
      <edge toID="1.54" type="E">
        <attributes />
      </edge>
      <edge toID="1.55" type="E">
        <attributes />
      </edge>
      <edge toID="1.56" type="C">
        <attributes />
      </edge>
    </node>
    <node ID="1.45" type="FN">
      <attributes />
      <edge toID="1.46" type="R">
        <attributes />
      </edge>
      <edge toID="1.47" type="E">
        <attributes />
      </edge>
      <edge toID="1.48" type="E">
        <attributes />
      </edge>
      <edge toID="1.49" type="E">
        <attributes />
      </edge>
      <edge toID="1.50" type="C">
        <attributes />
      </edge>
    </node>
    <node ID="1.46" type="FN">
      <attributes />
      <edge toID="0.14" type="Terminal">
        <attributes />
      </edge>
    </node>
    <node ID="1.47" type="FN">
      <attributes />
      <edge toID="0.15" type="Terminal">
        <attributes />
      </edge>
    </node>
    <node ID="1.48" type="FN">
      <attributes />
      <edge toID="1.51" type="C">
        <attributes />
      </edge>
      <edge toID="1.52" type="R">
        <attributes />
      </edge>
    </node>
    <node ID="1.49" type="FN">
      <attributes />
      <edge toID="0.18" type="Terminal">
        <attributes />
      </edge>
    </node>
    <node ID="1.50" type="FN">
      <attributes />
      <edge toID="0.19" type="Terminal">
        <attributes />
      </edge>
    </node>
    <node ID="1.51" type="FN">
      <attributes />
      <edge toID="0.16" type="Terminal">
        <attributes />
      </edge>
    </node>
    <node ID="1.52" type="FN">
      <attributes />
      <edge toID="0.17" type="Terminal">
        <attributes />
      </edge>
    </node>
    <node ID="1.53" type="FN">
      <attributes />
      <edge toID="0.10" type="Terminal">
        <attributes />
      </edge>
    </node>
    <node ID="1.54" type="FN">
      <attributes />
      <edge toID="0.11" type="Terminal">
        <attributes />
      </edge>
    </node>
    <node ID="1.55" type="FN">
      <attributes />
      <edge toID="0.12" type="Terminal">
        <attributes />
      </edge>
    </node>
    <node ID="1.56" type="FN">
      <attributes />
      <edge toID="0.13" type="Terminal">
        <attributes />
      </edge>
    </node>
    <node ID="1.57" type="FN">
      <attributes />
      <edge toID="0.8" type="Terminal">
        <attributes />
      </edge>
    </node>
    <node ID="1.58" type="FN">
      <attributes />
      <edge toID="0.9" type="Terminal">
        <attributes />
      </edge>
    </node>
  </layer>
</root>
